irakliotis_comp180/__init__.py
irakliotis_comp180/constants.py
irakliotis_comp180/utilities.py
irakliotis_comp180_utilities-0.0.6.dist-info/LICENSE
irakliotis_comp180_utilities-0.0.6.dist-info/METADATA
irakliotis_comp180_utilities-0.0.6.dist-info/WHEEL
irakliotis_comp180_utilities-0.0.6.dist-info/top_level.txt
irakliotis_comp180_utilities-0.0.6.dist-info/RECORD
