Metadata-Version: 2.1
Name: irakliotis-comp180-utilities
Version: 0.0.6
Summary: Utilities for COMP 180 at LUC
Home-page: https://github.com/lgreco
Author: Leo Irakliotis
Author-email: lgreco@gmail.com
License: UNKNOWN
Project-URL: Bug Tracker, https://github.com/pypa/sampleproject/issues
Platform: UNKNOWN
Classifier: Programming Language :: Python :: 3
Classifier: License :: OSI Approved :: MIT License
Classifier: Operating System :: OS Independent
Requires-Python: >=3.6
License-File: LICENSE
